{
  "downloadedAt": "2026-07-02T08:19:19.849Z",
  "word": {
    "id": "en-gb-word-town",
    "written": "town",
    "ipa": "/taʊn/",
    "phonemeIds": [
      "en-gb-t",
      "en-gb-mouth",
      "en-gb-n"
    ]
  },
  "candidate": {
    "fileTitle": "File:LL-Q1860 (eng)-Naomi Persephone Amethyst (NaomiAmethyst)-town.wav",
    "audioUrl": "https://upload.wikimedia.org/wikipedia/commons/8/8b/LL-Q1860_%28eng%29-Naomi_Persephone_Amethyst_%28NaomiAmethyst%29-town.wav",
    "commonsUrl": "https://commons.wikimedia.org/wiki/File:LL-Q1860_(eng)-Naomi_Persephone_Amethyst_(NaomiAmethyst)-town.wav",
    "mime": "audio/wav",
    "size": 79916,
    "license": "cc-by-sa-4.0",
    "licenseShortName": "CC BY-SA 4.0",
    "artist": "Speaker: Naomi Persephone Amethyst Recorder: NaomiAmethyst",
    "credit": "Own work",
    "attribution": null,
    "description": "Audio pronunciation file from the Lingua Libre project.",
    "key": "en-gb-word-town|File%3ALL-Q1860%20(eng)-Naomi%20Persephone%20Amethyst%20(NaomiAmethyst)-town.wav|https%3A%2F%2Fcommons.wikimedia.org%2Fwiki%2FFile%3ALL-Q1860_(eng)-Naomi_Persephone_Amethyst_(NaomiAmethyst)-town.wav",
    "sourceWikis": [
      "en.wiktionary.org"
    ],
    "regions": [],
    "wiktionaryIpaClaims": [
      {
        "wiki": "en.wiktionary.org",
        "pageTitle": "town",
        "fileTitle": "File:LL-Q1860 (eng)-Naomi Persephone Amethyst (NaomiAmethyst)-town.wav",
        "languageCode": "en",
        "ipa": "/ˈtaʊ̯n/",
        "normalizedIpa": "taʊn",
        "context": "* {{IPA|en|/ˈtaʊ̯n/|[ˈtʰaʊ̯n]|a=RP,GA}}"
      },
      {
        "wiki": "en.wiktionary.org",
        "pageTitle": "town",
        "fileTitle": "File:LL-Q1860 (eng)-Naomi Persephone Amethyst (NaomiAmethyst)-town.wav",
        "languageCode": "en",
        "ipa": "[ˈtʰaʊ̯n]",
        "normalizedIpa": "tʰaʊn",
        "context": "* {{IPA|en|/ˈtaʊ̯n/|[ˈtʰaʊ̯n]|a=RP,GA}}"
      }
    ],
    "ipaCheck": {
      "status": "match",
      "expected": "/taʊn/",
      "claimed": [
        "/ˈtaʊ̯n/",
        "[ˈtʰaʊ̯n]"
      ],
      "matched": [
        "/ˈtaʊ̯n/"
      ]
    },
    "score": 19,
    "reasons": [
      "file metadata/title contains word",
      "metadata suggests English audio",
      "found on primary Wiktionary page",
      "audio MIME audio/wav",
      "Wiktionary IPA matches /taʊn/"
    ],
    "suggestedAudioSource": {
      "src": "audio/en-gb/wiktionary/en-gb-word-town/LL-Q1860__eng_-Naomi_Persephone_Amethyst__NaomiAmethyst_-town.wav",
      "kind": "wiktionary",
      "license": "CC BY-SA 4.0",
      "attribution": "Speaker: Naomi Persephone Amethyst Recorder: NaomiAmethyst",
      "sourceUrl": "https://commons.wikimedia.org/wiki/File:LL-Q1860_(eng)-Naomi_Persephone_Amethyst_(NaomiAmethyst)-town.wav"
    },
    "review": {
      "status": "approved"
    },
    "localPath": "public/audio/en-gb/wiktionary/en-gb-word-town/LL-Q1860__eng_-Naomi_Persephone_Amethyst__NaomiAmethyst_-town.wav",
    "metadataPath": "public/audio/en-gb/wiktionary/en-gb-word-town/LL-Q1860__eng_-Naomi_Persephone_Amethyst__NaomiAmethyst_-town.wav.metadata.json",
    "datasetSrc": "audio/en-gb/wiktionary/en-gb-word-town/LL-Q1860__eng_-Naomi_Persephone_Amethyst__NaomiAmethyst_-town.wav"
  }
}
